ai_mcp_terminal-1.3.40.dist-info/licenses/LICENSE
src/__init__.py
src/main.py
src/mcp_server.py
src/terminal_manager.py
src/web_server.py
src/static/app.js
src/static/index.html
src/static/styles.css
ai_mcp_terminal-1.3.40.dist-info/METADATA
ai_mcp_terminal-1.3.40.dist-info/WHEEL
ai_mcp_terminal-1.3.40.dist-info/entry_points.txt
ai_mcp_terminal-1.3.40.dist-info/top_level.txt
ai_mcp_terminal-1.3.40.dist-info/RECORD
