Metadata-Version: 2.4
Name: ai-mcp-terminal
Version: 1.3.40
Summary: 多线程AI终端管理器 - 支持MCP协议，具有智能内存管理、多终端并发执行、实时Web界面
Home-page: https://github.com/yourusername/ai-mcp-terminal
Author: Your Name
Author-email: Your Name <your.email@example.com>
License: MIT
Project-URL: Homepage, https://github.com/yourusername/ai-mcp-terminal
Project-URL: Documentation, https://github.com/yourusername/ai-mcp-terminal#readme
Project-URL: Repository, https://github.com/yourusername/ai-mcp-terminal
Project-URL: Issues, https://github.com/yourusername/ai-mcp-terminal/issues
Keywords: mcp,terminal,ai,multi-thread,concurrent,shell,management
Classifier: Development Status :: 4 - Beta
Classifier: Intended Audience :: Developers
Classifier: Topic :: Software Development :: Libraries :: Python Modules
Classifier: License :: OSI Approved :: MIT License
Classifier: Programming Language :: Python :: 3
Classifier: Programming Language :: Python :: 3.8
Classifier: Programming Language :: Python :: 3.9
Classifier: Programming Language :: Python :: 3.10
Classifier: Programming Language :: Python :: 3.11
Classifier: Programming Language :: Python :: 3.12
Classifier: Operating System :: OS Independent
Classifier: Framework :: FastAPI
Requires-Python: >=3.8
License-File: LICENSE
Requires-Dist: mcp>=1.0.0
Requires-Dist: fastapi>=0.104.0
Requires-Dist: uvicorn[standard]>=0.24.0
Requires-Dist: websockets>=12.0
Requires-Dist: psutil>=5.9.0
Requires-Dist: aiofiles>=23.2.0
Requires-Dist: python-multipart>=0.0.6
Dynamic: author
Dynamic: home-page
Dynamic: license-file
Dynamic: requires-python
